quickcsv/__init__.py
quickcsv/file.py
quickcsv/largefile.py
quickcsv/__pycache__/__init__.cpython-36.pyc
quickcsv/__pycache__/__init__.cpython-39.pyc
quickcsv/__pycache__/file.cpython-36.pyc
quickcsv/__pycache__/file.cpython-39.pyc
quickcsv/__pycache__/largefile.cpython-39.pyc
quick_csv-0.0.5.dist-info/LICENSE
quick_csv-0.0.5.dist-info/METADATA
quick_csv-0.0.5.dist-info/WHEEL
quick_csv-0.0.5.dist-info/top_level.txt
quick_csv-0.0.5.dist-info/RECORD
